{
  "kind": "collectionType",
  "collectionName": "contact_us_froms",
  "info": {
    "singularName": "contact-us-from",
    "pluralName": "contact-us-froms",
    "displayName": "contact-us-from",
    "description": ""
  },
  "options": {
    "draftAndPublish": false
  },
  "pluginOptions": {},
  "attributes": {
    "first_name": {
      "type": "string",
      "required": false
    },
    "last_name": {
      "type": "string",
      "required": false
    },
    "email": {
      "type": "email",
      "required": false
    },
    "mobile": {
      "type": "string"
    },
    "subject": {
      "type": "text"
    },
    "message": {
      "type": "text"
    }
  }
}
